<?xml version="1.0" encoding="UTF-8"?>
<comment version="3.0">
  <caption/>
  <note>Grandmother happy emotion avatar. Face Grandma merry emoji. Old lady Vector illustration</note>
  <place/>
  <categories>
    <category value="grandmother"/>
    <category value="old"/>
    <category value="female"/>
    <category value="person"/>
    <category value="senior"/>
    <category value="people"/>
    <category value="portrait"/>
    <category value="happy"/>
    <category value="woman"/>
    <category value="smile"/>
    <category value="elderly"/>
    <category value="caucasian"/>
    <category value="white"/>
    <category value="pensioner"/>
    <category value="age"/>
    <category value="older"/>
    <category value="adult"/>
    <category value="one"/>
    <category value="face"/>
    <category value="mother"/>
    <category value="retired"/>
    <category value="lady"/>
    <category value="isolated"/>
    <category value="mature"/>
    <category value="background"/>
    <category value="beautiful"/>
    <category value="hand"/>
    <category value="cheerful"/>
    <category value="lifestyle"/>
    <category value="healthy"/>
    <category value="natural"/>
    <category value="aged"/>
    <category value="retirement"/>
    <category value="alone"/>
    <category value="single"/>
    <category value="happiness"/>
    <category value="human"/>
    <category value="grandma"/>
    <category value="hair"/>
    <category value="active"/>
    <category value="gray"/>
    <category value="attractive"/>
    <category value="european"/>
    <category value="success"/>
    <category value="closeup"/>
    <category value="confident"/>
    <category value="health"/>
    <category value="fun"/>
    <category value="friendly"/>
    <category value="granny"/>
  </categories>
</comment>
